cloudproof_py/__init__.py
cloudproof_py/py.typed
cloudproof_py/anonymization/__init__.py
cloudproof_py/cover_crypt/__init__.py
cloudproof_py/findex/__init__.py
cloudproof_py/findex/typing.py
cloudproof_py/findex/utils.py
cloudproof_py/fpe/__init__.py
cloudproof_py/kms/__init__.py
cloudproof_py-5.0.0.dist-info/LICENSE.md
cloudproof_py-5.0.0.dist-info/METADATA
cloudproof_py-5.0.0.dist-info/WHEEL
cloudproof_py-5.0.0.dist-info/top_level.txt
cloudproof_py-5.0.0.dist-info/RECORD
