Metadata-Version: 2.1
Name: cloudproof-py
Version: 5.0.0
Summary: Python library for Cosmian Cloudproof
Author-email: Cosmian Tech <tech@cosmian.com>
Project-URL: Homepage, https://github.com/Cosmian/cloudproof_python
Project-URL: Bug Tracker, https://github.com/Cosmian/cloudproof_python/issues
Classifier: Programming Language :: Python :: 3
Classifier: Operating System :: OS Independent
Requires-Python: >=3.7
License-File: LICENSE.md
Requires-Dist: cloudproof-anonymization <1.0.0,>=0.1.0
Requires-Dist: cover-crypt <15.0.0,>=14.0.0
Requires-Dist: findex <7.0.0,>=6.0.0
Requires-Dist: cosmian-kms <5.0.0,>=4.13.0
Requires-Dist: cloudproof-fpe <1.0.0,>=0.1.0
